{
  "version-4.3.0/docs": [
    {
      "collapsed": false,
      "type": "category",
      "label": "AWE framework",
      "items": [
        {
          "type": "doc",
          "id": "version-4.3.0/intro"
        },
        {
          "type": "doc",
          "id": "version-4.3.0/purpose"
        },
        {
          "type": "doc",
          "id": "version-4.3.0/architecture"
        },
        {
          "type": "doc",
          "id": "version-4.3.0/security"
        }
      ]
    },
    {
      "collapsed": true,
      "type": "category",
      "label": "Getting Started",
      "items": [
        {
          "type": "doc",
          "id": "version-4.3.0/installation"
        },
        {
          "collapsed": true,
          "type": "category",
          "label": "Configuration",
          "items": [
            {
              "type": "doc",
              "id": "version-4.3.0/maven"
            },
            {
              "collapsed": true,
              "type": "category",
              "label": "Modules",
              "items": [
                {
                  "type": "doc",
                  "id": "version-4.3.0/annotations"
                },
                {
                  "type": "doc",
                  "id": "version-4.3.0/developer-tools"
                },
                {
                  "type": "doc",
                  "id": "version-4.3.0/builder"
                },
                {
                  "type": "doc",
                  "id": "version-4.3.0/rest"
                },
                {
                  "type": "doc",
                  "id": "version-4.3.0/scheduler"
                },
                {
                  "type": "doc",
                  "id": "version-4.3.0/notifier"
                },
                {
                  "type": "doc",
                  "id": "version-4.3.0/database-migration"
                }
              ]
            },
            {
              "type": "doc",
              "id": "version-4.3.0/properties"
            },
            {
              "type": "doc",
              "id": "version-4.3.0/application-options"
            },
            {
              "type": "doc",
              "id": "version-4.3.0/session"
            }
          ]
        },
        {
          "type": "doc",
          "id": "version-4.3.0/deployment"
        }
      ]
    },
    {
      "collapsed": true,
      "type": "category",
      "label": "Guides",
      "items": [
        {
          "type": "doc",
          "id": "version-4.3.0/guides/project-structure"
        },
        {
          "type": "doc",
          "id": "version-4.3.0/guides/scheduler"
        },
        {
          "type": "doc",
          "id": "version-4.3.0/guides/notifier"
        },
        {
          "type": "doc",
          "id": "version-4.3.0/guides/selenium-testing"
        },
        {
          "type": "doc",
          "id": "version-4.3.0/guides/print-engine"
        },
        {
          "type": "doc",
          "id": "version-4.3.0/guides/debugging"
        },
        {
          "type": "doc",
          "id": "version-4.3.0/guides/validation"
        },
        {
          "type": "doc",
          "id": "version-4.3.0/guides/v4-migration"
        },
        {
          "type": "doc",
          "id": "version-4.3.0/guides/default-screens"
        }
      ]
    },
    {
      "collapsed": true,
      "type": "category",
      "label": "API Reference",
      "items": [
        {
          "type": "doc",
          "id": "version-4.3.0/api/screens"
        },
        {
          "type": "doc",
          "id": "version-4.3.0/api/menu"
        },
        {
          "type": "doc",
          "id": "version-4.3.0/api/enumerate"
        },
        {
          "type": "doc",
          "id": "version-4.3.0/api/query"
        },
        {
          "type": "doc",
          "id": "version-4.3.0/api/maintain"
        },
        {
          "type": "doc",
          "id": "version-4.3.0/api/service"
        },
        {
          "type": "doc",
          "id": "version-4.3.0/api/queues"
        },
        {
          "type": "doc",
          "id": "version-4.3.0/api/email"
        },
        {
          "type": "doc",
          "id": "version-4.3.0/api/i18n-internationalization"
        }
      ]
    }
  ],
  "version-4.3.0/screens": [
    {
      "type": "ref",
      "id": "version-4.3.0/api/screens"
    },
    {
      "collapsed": false,
      "type": "category",
      "label": "API Reference",
      "items": [
        {
          "type": "doc",
          "id": "version-4.3.0/api/screen"
        },
        {
          "type": "doc",
          "id": "version-4.3.0/api/template"
        },
        {
          "type": "doc",
          "id": "version-4.3.0/api/layout"
        },
        {
          "type": "doc",
          "id": "version-4.3.0/api/tags"
        },
        {
          "type": "doc",
          "id": "version-4.3.0/api/window"
        },
        {
          "type": "doc",
          "id": "version-4.3.0/api/resizable"
        },
        {
          "type": "doc",
          "id": "version-4.3.0/api/button"
        },
        {
          "type": "doc",
          "id": "version-4.3.0/api/criteria"
        },
        {
          "type": "doc",
          "id": "version-4.3.0/api/tab-and-tabcontainer"
        },
        {
          "type": "doc",
          "id": "version-4.3.0/api/wizard-and-wizard-panel"
        },
        {
          "type": "doc",
          "id": "version-4.3.0/api/accordion"
        },
        {
          "type": "doc",
          "id": "version-4.3.0/api/grids"
        },
        {
          "type": "doc",
          "id": "version-4.3.0/api/pivot-table"
        },
        {
          "type": "doc",
          "id": "version-4.3.0/api/context-menu"
        },
        {
          "type": "doc",
          "id": "version-4.3.0/api/messages"
        },
        {
          "type": "doc",
          "id": "version-4.3.0/api/info"
        },
        {
          "type": "doc",
          "id": "version-4.3.0/api/include"
        },
        {
          "type": "doc",
          "id": "version-4.3.0/api/dialog"
        },
        {
          "type": "doc",
          "id": "version-4.3.0/api/chart"
        },
        {
          "type": "doc",
          "id": "version-4.3.0/api/actions"
        },
        {
          "type": "doc",
          "id": "version-4.3.0/api/dependencies"
        }
      ]
    }
  ],
  "version-4.3.0/schedule": [
    {
      "type": "ref",
      "id": "version-4.3.0/guides/scheduler"
    },
    {
      "collapsed": false,
      "type": "category",
      "label": "Schedule Task",
      "items": [
        {
          "type": "doc",
          "id": "version-4.3.0/guides/schedule-configuration"
        },
        {
          "type": "doc",
          "id": "version-4.3.0/guides/dependency-task"
        }
      ]
    }
  ],
  "version-4.3.0/training": [
    {
      "collapsed": false,
      "type": "category",
      "label": "Basic tutorials",
      "items": [
        {
          "type": "doc",
          "id": "version-4.3.0/training/awe-101"
        },
        {
          "type": "doc",
          "id": "version-4.3.0/training/awe-102"
        },
        {
          "type": "doc",
          "id": "version-4.3.0/training/awe-103"
        },
        {
          "type": "doc",
          "id": "version-4.3.0/training/awe-104"
        },
        {
          "type": "doc",
          "id": "version-4.3.0/training/awe-105"
        },
        {
          "type": "doc",
          "id": "version-4.3.0/training/awe-106"
        },
        {
          "type": "doc",
          "id": "version-4.3.0/training/awe-107"
        },
        {
          "type": "doc",
          "id": "version-4.3.0/training/awe-108"
        }
      ]
    }
  ]
}
